dcre/__init__.py
dcre/_version.py
dcre/cre_decomposition.py
dcre/erfani_2022/__init__.py
dcre/erfani_2022/erfani_2022_results.py
dcre/erfani_2022/erfani_decomp_func.py
dcre/erfani_2022/erfani_output_decomp_new.py
dcre/erfani_2022/erfani_output_decomp_orig.py
dcre/erfani_2022/helpers.py
dcre/erfani_2022/figures/__init__.py
dcre/erfani_2022/figures/cre_timeseries.py
dcre/erfani_2022/figures/erfani_2022_fig13.py
dcre/erfani_2022/figures/erfani_2022_fig14.py
dcre/erfani_2022/figures/transition_timeseries.py
tests/test_erfani_2022_figures.py
tests/test_erfani_2022_results.py
tests/test_idealized_scenes.py
dcre-2023.2.4.dist-info/METADATA
dcre-2023.2.4.dist-info/WHEEL
dcre-2023.2.4.dist-info/top_level.txt
dcre-2023.2.4.dist-info/RECORD
