Metadata-Version: 2.1
Name: dcre
Version: 2023.2.4
Summary: Python package for CRE processing
Author: Hauke Schulz
Classifier: Programming Language :: Python :: 3.10
Classifier: Programming Language :: Python :: 3.11
Requires-Python: >=3.9
Requires-Dist: matplotlib
Requires-Dist: numpy
Requires-Dist: xarray
Requires-Dist: seaborn
